metazimmer/__init__.py
metazimmer/tests/test_init.py
metazimmer-0.0.0.dist-info/LICENSE
metazimmer-0.0.0.dist-info/WHEEL
metazimmer-0.0.0.dist-info/METADATA
metazimmer-0.0.0.dist-info/RECORD
