Metadata-Version: 2.1
Name: metazimmer
Version: 0.0.0
Summary: Datazimmer helper
Author-email: Endre Márk Borza <endremborza@gmail.com>
Requires-Python: >=3.8
Requires-Dist: branthebuilder[doc] ; extra == "doc"
Requires-Dist: branthebuilder ; extra == "test"
Project-URL: Homepage, https://github.com/endremborza/metazimmer
Provides-Extra: doc
Provides-Extra: test
